{
  "generated_at_utc": "2026-03-13T19:31:36.695984+00:00",
  "source_modeling_input_path": "data\\modeling\\entsoe\\ireland_load_modeling_table.csv",
  "source_weather_input_path": "data\\processed\\weather\\nasa_power_weather_hourly.csv",
  "weather_feature_columns": [
    "temp_2m_c",
    "rel_humidity_2m_pct",
    "wind_speed_10m_ms",
    "wind_direction_10m_deg",
    "surface_pressure_kpa",
    "precipitation_mm_hr",
    "allsky_surface_solar_downward_wm2"
  ],
  "quality_summary": {
    "row_count": 8784,
    "start_utc": "2024-01-01 00:00:00+00:00",
    "end_utc": "2024-12-31 23:00:00+00:00",
    "target_missing_row_count": 68,
    "wind_missing_row_count": 98,
    "weather_quality": {
      "temp_2m_c": {
        "raw_missing_count": 0,
        "postfill_missing_count": 0
      },
      "rel_humidity_2m_pct": {
        "raw_missing_count": 0,
        "postfill_missing_count": 0
      },
      "wind_speed_10m_ms": {
        "raw_missing_count": 0,
        "postfill_missing_count": 0
      },
      "wind_direction_10m_deg": {
        "raw_missing_count": 0,
        "postfill_missing_count": 0
      },
      "surface_pressure_kpa": {
        "raw_missing_count": 0,
        "postfill_missing_count": 0
      },
      "precipitation_mm_hr": {
        "raw_missing_count": 0,
        "postfill_missing_count": 0
      },
      "allsky_surface_solar_downward_wm2": {
        "raw_missing_count": 0,
        "postfill_missing_count": 0
      }
    }
  },
  "note": "This artifact extends the prior ENTSO-E modeling table with NASA POWER hourly weather covariates."
}